[{
    "amount": 15793700235.7,
    "date": 1639099800000,
    "index": 0,
    "price": 3656.9477,
    "volume": 1351192900
}, {
    "amount": 7176205730.6,
    "date": 1639099860000,
    "index": 1,
    "price": 3657.1655,
    "volume": 595049600
}, {
    "amount": 6409968449.3,
    "date": 1639099920000,
    "index": 2,
    "price": 3656.8601,
    "volume": 530479900
}, {
    "amount": 6382645584.6,
    "date": 1639099980000,
    "index": 3,
    "price": 3659.4554,
    "volume": 532222000
}, {
    "amount": 6096063771.1,
    "date": 1639100040000,
    "index": 4,
    "price": 3656.5075,
    "volume": 502437400
}, {
    "amount": 5912292505.5,
    "date": 1639100100000,
    "index": 5,
    "price": 3654.8726,
    "volume": 485958300
}, {
    "amount": 5596694480.3,
    "date": 1639100160000,
    "index": 6,
    "price": 3654.9994,
    "volume": 452532100
}, {
    "amount": 5064174951.3,
    "date": 1639100220000,
    "index": 7,
    "price": 3652.505,
    "volume": 418396000
}, {
    "amount": 4811354395.6,
    "date": 1639100280000,
    "index": 8,
    "price": 3652.995,
    "volume": 380873900
}, {
    "amount": 4768870299,
    "date": 1639100340000,
    "index": 9,
    "price": 3654.2869,
    "volume": 413785100
}, {
    "amount": 5079138887.9,
    "date": 1639100400000,
    "index": 10,
    "price": 3654.8629,
    "volume": 417312400
}, {
    "amount": 4819271641.7,
    "date": 1639100460000,
    "index": 11,
    "price": 3658.7186,
    "volume": 402102500
}, {
    "amount": 4505750053.9,
    "date": 1639100520000,
    "index": 12,
    "price": 3659.9388,
    "volume": 357960700
}, {
    "amount": 4248641314.1,
    "date": 1639100580000,
    "index": 13,
    "price": 3658.165,
    "volume": 328987700
}, {
    "amount": 4636218157.6,
    "date": 1639100640000,
    "index": 14,
    "price": 3660.4602,
    "volume": 382083000
}, {
    "amount": 4405678534.6,
    "date": 1639100700000,
    "index": 15,
    "price": 3659.2567,
    "volume": 343569900
}, {
    "amount": 4174408937.6,
    "date": 1639100760000,
    "index": 16,
    "price": 3658.3093,
    "volume": 311807100
}, {
    "amount": 4017948047.3,
    "date": 1639100820000,
    "index": 17,
    "price": 3656.9569,
    "volume": 302286400
}, {
    "amount": 4046494526.4,
    "date": 1639100880000,
    "index": 18,
    "price": 3655.8963,
    "volume": 309445300
}, {
    "amount": 3836138967.1,
    "date": 1639100940000,
    "index": 19,
    "price": 3657.1872,
    "volume": 269104100
}, {
    "amount": 4293681090.6,
    "date": 1639101000000,
    "index": 20,
    "price": 3659.1251,
    "volume": 303362200
}, {
    "amount": 3577803098.9,
    "date": 1639101060000,
    "index": 21,
    "price": 3661.7312,
    "volume": 263190200
}, {
    "amount": 3588985103.5,
    "date": 1639101120000,
    "index": 22,
    "price": 3661.0734,
    "volume": 275224700
}, {
    "amount": 3278419806.7,
    "date": 1639101180000,
    "index": 23,
    "price": 3662.5725,
    "volume": 241981500
}, {
    "amount": 3343865155.6,
    "date": 1639101240000,
    "index": 24,
    "price": 3662.4675,
    "volume": 239393400
}, {
    "amount": 3486260096.1,
    "date": 1639101300000,
    "index": 25,
    "price": 3664.5789,
    "volume": 249384100
}, {
    "amount": 3175029640.1,
    "date": 1639101360000,
    "index": 26,
    "price": 3664.2646,
    "volume": 241743400
}, {
    "amount": 3121642609.8,
    "date": 1639101420000,
    "index": 27,
    "price": 3661.2903,
    "volume": 218549400
}, {
    "amount": 2898381742,
    "date": 1639101480000,
    "index": 28,
    "price": 3661.3437,
    "volume": 216900400
}, {
    "amount": 2852803203.4,
    "date": 1639101540000,
    "index": 29,
    "price": 3661.5799,
    "volume": 206816100
}, {
    "amount": 3751201777.8,
    "date": 1639101600000,
    "index": 30,
    "price": 3663.044,
    "volume": 263075400
}, {
    "amount": 3401622882.3,
    "date": 1639101660000,
    "index": 31,
    "price": 3661.4161,
    "volume": 243954300
}, {
    "amount": 3131434560,
    "date": 1639101720000,
    "index": 32,
    "price": 3663.4173,
    "volume": 210032600
}, {
    "amount": 2877867684.3,
    "date": 1639101780000,
    "index": 33,
    "price": 3663.7857,
    "volume": 210956500
}, {
    "amount": 2977952356.7,
    "date": 1639101840000,
    "index": 34,
    "price": 3663.3732,
    "volume": 218653000
}, {
    "amount": 2836249119.6,
    "date": 1639101900000,
    "index": 35,
    "price": 3661.8209,
    "volume": 204542300
}, {
    "amount": 2868979840.6,
    "date": 1639101960000,
    "index": 36,
    "price": 3660.8674,
    "volume": 200651400
}, {
    "amount": 2968443584.5,
    "date": 1639102020000,
    "index": 37,
    "price": 3660.9701,
    "volume": 200475300
}, {
    "amount": 2761993737.7,
    "date": 1639102080000,
    "index": 38,
    "price": 3660.573,
    "volume": 189467700
}, {
    "amount": 3091074785.8,
    "date": 1639102140000,
    "index": 39,
    "price": 3660.2536,
    "volume": 223787800
}, {
    "amount": 2873650289.6,
    "date": 1639102200000,
    "index": 40,
    "price": 3659.1399,
    "volume": 207300100
}, {
    "amount": 2789384024.5,
    "date": 1639102260000,
    "index": 41,
    "price": 3659.9686,
    "volume": 205459300
}, {
    "amount": 2606053559.2,
    "date": 1639102320000,
    "index": 42,
    "price": 3659.9618,
    "volume": 189508200
}, {
    "amount": 2450092487.6,
    "date": 1639102380000,
    "index": 43,
    "price": 3661.5215,
    "volume": 191490500
}, {
    "amount": 2447826655.6,
    "date": 1639102440000,
    "index": 44,
    "price": 3662.7693,
    "volume": 169809200
}, {
    "amount": 2566912581,
    "date": 1639102500000,
    "index": 45,
    "price": 3662.9558,
    "volume": 172160800
}, {
    "amount": 2663878808.1,
    "date": 1639102560000,
    "index": 46,
    "price": 3663.7724,
    "volume": 187402800
}, {
    "amount": 2537410122.5,
    "date": 1639102620000,
    "index": 47,
    "price": 3665.7704,
    "volume": 177096300
}, {
    "amount": 2808827225,
    "date": 1639102680000,
    "index": 48,
    "price": 3663.7393,
    "volume": 209920100
}, {
    "amount": 2517137832.4,
    "date": 1639102740000,
    "index": 49,
    "price": 3663.4712,
    "volume": 172154800
}, {
    "amount": 2628492613.9,
    "date": 1639102800000,
    "index": 50,
    "price": 3665.2538,
    "volume": 174072100
}, {
    "amount": 2361782196.6,
    "date": 1639102860000,
    "index": 51,
    "price": 3665.8079,
    "volume": 165265300
}, {
    "amount": 2240806172.3,
    "date": 1639102920000,
    "index": 52,
    "price": 3664.5798,
    "volume": 161473100
}, {
    "amount": 2373682449.5,
    "date": 1639102980000,
    "index": 53,
    "price": 3666.3681,
    "volume": 172574500
}, {
    "amount": 2437179162,
    "date": 1639103040000,
    "index": 54,
    "price": 3664.2843,
    "volume": 192468800
}, {
    "amount": 2231736281.3,
    "date": 1639103100000,
    "index": 55,
    "price": 3663.9361,
    "volume": 169387400
}, {
    "amount": 2119311796.6,
    "date": 1639103160000,
    "index": 56,
    "price": 3662.2921,
    "volume": 167213700
}, {
    "amount": 2142717651.9,
    "date": 1639103220000,
    "index": 57,
    "price": 3662.7148,
    "volume": 186073200
}, {
    "amount": 2166221995.9,
    "date": 1639103280000,
    "index": 58,
    "price": 3663.3757,
    "volume": 165745800
}, {
    "amount": 2006824971.6,
    "date": 1639103340000,
    "index": 59,
    "price": 3662.7673,
    "volume": 141624700
}, {
    "amount": 2429811075.6,
    "date": 1639103400000,
    "index": 60,
    "price": 3665.8172,
    "volume": 176455900
}, {
    "amount": 2126689137.9,
    "date": 1639103460000,
    "index": 61,
    "price": 3663.624,
    "volume": 142975200
}, {
    "amount": 1818194884.9,
    "date": 1639103520000,
    "index": 62,
    "price": 3663.4181,
    "volume": 122474400
}, {
    "amount": 1974192175.8,
    "date": 1639103580000,
    "index": 63,
    "price": 3665.6617,
    "volume": 144123400
}, {
    "amount": 1825373995.1,
    "date": 1639103640000,
    "index": 64,
    "price": 3664.4657,
    "volume": 131338200
}, {
    "amount": 1784746520.3,
    "date": 1639103700000,
    "index": 65,
    "price": 3664.9332,
    "volume": 130216300
}, {
    "amount": 2112777893.1,
    "date": 1639103760000,
    "index": 66,
    "price": 3661.5789,
    "volume": 165918300
}, {
    "amount": 1855208848.4,
    "date": 1639103820000,
    "index": 67,
    "price": 3662.8266,
    "volume": 145702200
}, {
    "amount": 1843026741,
    "date": 1639103880000,
    "index": 68,
    "price": 3661.9563,
    "volume": 140053000
}, {
    "amount": 1814925197.5,
    "date": 1639103940000,
    "index": 69,
    "price": 3663.2479,
    "volume": 134636700
}, {
    "amount": 1775380242.6,
    "date": 1639104000000,
    "index": 70,
    "price": 3662.0535,
    "volume": 139450500
}, {
    "amount": 1663451868.5,
    "date": 1639104060000,
    "index": 71,
    "price": 3661.7471,
    "volume": 156095100
}, {
    "amount": 1731588282.8,
    "date": 1639104120000,
    "index": 72,
    "price": 3663.4133,
    "volume": 133522300
}, {
    "amount": 1951887367.6,
    "date": 1639104180000,
    "index": 73,
    "price": 3664.1235,
    "volume": 143237600
}, {
    "amount": 1605615016.1,
    "date": 1639104240000,
    "index": 74,
    "price": 3663.0084,
    "volume": 129766000
}, {
    "amount": 1769228486.6,
    "date": 1639104300000,
    "index": 75,
    "price": 3663.872,
    "volume": 136662700
}, {
    "amount": 1702497397.4,
    "date": 1639104360000,
    "index": 76,
    "price": 3665.112,
    "volume": 131394100
}, {
    "amount": 1807739819.7,
    "date": 1639104420000,
    "index": 77,
    "price": 3665.4705,
    "volume": 131221100
}, {
    "amount": 1737024350.8,
    "date": 1639104480000,
    "index": 78,
    "price": 3666.0206,
    "volume": 125295300
}, {
    "amount": 1827383420.3,
    "date": 1639104540000,
    "index": 79,
    "price": 3667.2562,
    "volume": 124356700
}, {
    "amount": 1916331761.4,
    "date": 1639104600000,
    "index": 80,
    "price": 3666.719,
    "volume": 128630000
}, {
    "amount": 1703211783.7,
    "date": 1639104660000,
    "index": 81,
    "price": 3667.191,
    "volume": 119712200
}, {
    "amount": 1670964249,
    "date": 1639104720000,
    "index": 82,
    "price": 3667.3477,
    "volume": 123705500
}, {
    "amount": 1679431753.6,
    "date": 1639104780000,
    "index": 83,
    "price": 3665.9223,
    "volume": 137797100
}, {
    "amount": 1525817314.1,
    "date": 1639104840000,
    "index": 84,
    "price": 3664.634,
    "volume": 111362600
}, {
    "amount": 1625658170.1,
    "date": 1639104900000,
    "index": 85,
    "price": 3665.7622,
    "volume": 115396700
}, {
    "amount": 1652931997.4,
    "date": 1639104960000,
    "index": 86,
    "price": 3664.6233,
    "volume": 109607500
}, {
    "amount": 1614061801.3,
    "date": 1639105020000,
    "index": 87,
    "price": 3664.0879,
    "volume": 110501700
}, {
    "amount": 1503157336,
    "date": 1639105080000,
    "index": 88,
    "price": 3663.3071,
    "volume": 120581500
}, {
    "amount": 1554872979.4,
    "date": 1639105140000,
    "index": 89,
    "price": 3663.9799,
    "volume": 114220000
}, {
    "amount": 1591759495.7,
    "date": 1639105200000,
    "index": 90,
    "price": 3663.9603,
    "volume": 112160400
}, {
    "amount": 1807639412.5,
    "date": 1639105260000,
    "index": 91,
    "price": 3662.3948,
    "volume": 142485400
}, {
    "amount": 1685974379.9,
    "date": 1639105320000,
    "index": 92,
    "price": 3663.5973,
    "volume": 127142400
}, {
    "amount": 1684101874.5,
    "date": 1639105380000,
    "index": 93,
    "price": 3664.9558,
    "volume": 127798100
}, {
    "amount": 1592156914.7,
    "date": 1639105440000,
    "index": 94,
    "price": 3663.6163,
    "volume": 130368900
}, {
    "amount": 1595852042.8,
    "date": 1639105500000,
    "index": 95,
    "price": 3662.6148,
    "volume": 122421300
}, {
    "amount": 1614241711.5,
    "date": 1639105560000,
    "index": 96,
    "price": 3661.5714,
    "volume": 139135800
}, {
    "amount": 1664366872.5,
    "date": 1639105620000,
    "index": 97,
    "price": 3660.8325,
    "volume": 140626900
}, {
    "amount": 1617636044.9,
    "date": 1639105680000,
    "index": 98,
    "price": 3661.444,
    "volume": 139221900
}, {
    "amount": 1524635028.6,
    "date": 1639105740000,
    "index": 99,
    "price": 3661.2607,
    "volume": 130940100
}, {
    "amount": 1526095742.8,
    "date": 1639105800000,
    "index": 100,
    "price": 3662.0922,
    "volume": 118798100
}, {
    "amount": 1489682867.9,
    "date": 1639105860000,
    "index": 101,
    "price": 3661.6061,
    "volume": 111702200
}, {
    "amount": 1351477863.8,
    "date": 1639105920000,
    "index": 102,
    "price": 3661.7273,
    "volume": 101641700
}, {
    "amount": 1479966012.6,
    "date": 1639105980000,
    "index": 103,
    "price": 3659.6149,
    "volume": 102327900
}, {
    "amount": 1454203178.8,
    "date": 1639106040000,
    "index": 104,
    "price": 3660.1013,
    "volume": 111707800
}, {
    "amount": 1546405152.1,
    "date": 1639106100000,
    "index": 105,
    "price": 3660.014,
    "volume": 118615000
}, {
    "amount": 1445741051.2,
    "date": 1639106160000,
    "index": 106,
    "price": 3660.04,
    "volume": 109809400
}, {
    "amount": 1446375793.6,
    "date": 1639106220000,
    "index": 107,
    "price": 3661.3999,
    "volume": 106022500
}, {
    "amount": 1415787785.1,
    "date": 1639106280000,
    "index": 108,
    "price": 3661.0684,
    "volume": 102422400
}, {
    "amount": 1391595560.2,
    "date": 1639106340000,
    "index": 109,
    "price": 3659.8543,
    "volume": 102397300
}, {
    "amount": 1513007053,
    "date": 1639106400000,
    "index": 110,
    "price": 3660.0189,
    "volume": 110067100
}, {
    "amount": 1601771399.9,
    "date": 1639106460000,
    "index": 111,
    "price": 3662.3371,
    "volume": 119933000
}, {
    "amount": 1368983783.7,
    "date": 1639106520000,
    "index": 112,
    "price": 3661.9526,
    "volume": 93755000
}, {
    "amount": 1362032446.8,
    "date": 1639106580000,
    "index": 113,
    "price": 3662.083,
    "volume": 92342900
}, {
    "amount": 1411041238.7,
    "date": 1639106640000,
    "index": 114,
    "price": 3661.7023,
    "volume": 102919000
}, {
    "amount": 1399045098.6,
    "date": 1639106700000,
    "index": 115,
    "price": 3662.3122,
    "volume": 108658100
}, {
    "amount": 1346337494.6,
    "date": 1639106760000,
    "index": 116,
    "price": 3660.911,
    "volume": 96962400
}, {
    "amount": 1320832291.1,
    "date": 1639106820000,
    "index": 117,
    "price": 3661.7837,
    "volume": 92725600
}, {
    "amount": 1293060859.8,
    "date": 1639106880000,
    "index": 118,
    "price": 3661.8897,
    "volume": 95517100
}, {
    "amount": 1429248131,
    "date": 1639106940000,
    "index": 119,
    "price": 3661.0652,
    "volume": 113625500
}, {
    "amount": 17081363.3,
    "date": 1639107000000,
    "index": 120,
    "price": 3661.1205,
    "volume": 2027400
}, {
    "amount": 3591469818.2,
    "date": 1639112400000,
    "index": 121,
    "price": 3662.6319,
    "volume": 306656900
}, {
    "amount": 1801549070.4,
    "date": 1639112460000,
    "index": 122,
    "price": 3662.5141,
    "volume": 124439600
}, {
    "amount": 1950108323.9,
    "date": 1639112520000,
    "index": 123,
    "price": 3662.5365,
    "volume": 147786100
}, {
    "amount": 1657902724.4,
    "date": 1639112580000,
    "index": 124,
    "price": 3661.3876,
    "volume": 136414300
}, {
    "amount": 1733227976.3,
    "date": 1639112640000,
    "index": 125,
    "price": 3664.1902,
    "volume": 119225800
}, {
    "amount": 1766240235.6,
    "date": 1639112700000,
    "index": 126,
    "price": 3665.2354,
    "volume": 132236500
}, {
    "amount": 1654737936,
    "date": 1639112760000,
    "index": 127,
    "price": 3663.9474,
    "volume": 125709300
}, {
    "amount": 1601504210.2,
    "date": 1639112820000,
    "index": 128,
    "price": 3665.5578,
    "volume": 116240400
}, {
    "amount": 1690000230,
    "date": 1639112880000,
    "index": 129,
    "price": 3665.2449,
    "volume": 127334500
}, {
    "amount": 1582207025.1,
    "date": 1639112940000,
    "index": 130,
    "price": 3665.5504,
    "volume": 124190200
}, {
    "amount": 1857420260.7,
    "date": 1639113000000,
    "index": 131,
    "price": 3666.4721,
    "volume": 138308300
}, {
    "amount": 1651016120.6,
    "date": 1639113060000,
    "index": 132,
    "price": 3667.4283,
    "volume": 122918400
}, {
    "amount": 1678960478.3,
    "date": 1639113120000,
    "index": 133,
    "price": 3667.1171,
    "volume": 125828000
}, {
    "amount": 1561241852.1,
    "date": 1639113180000,
    "index": 134,
    "price": 3666.4285,
    "volume": 116310100
}, {
    "amount": 1616146437.1,
    "date": 1639113240000,
    "index": 135,
    "price": 3665.1036,
    "volume": 114905500
}, {
    "amount": 1710790711.6,
    "date": 1639113300000,
    "index": 136,
    "price": 3666.1721,
    "volume": 118841300
}, {
    "amount": 1576372578.1,
    "date": 1639113360000,
    "index": 137,
    "price": 3664.3852,
    "volume": 114074500
}, {
    "amount": 1613710926.1,
    "date": 1639113420000,
    "index": 138,
    "price": 3665.3029,
    "volume": 116669500
}, {
    "amount": 1795943704.3,
    "date": 1639113480000,
    "index": 139,
    "price": 3664.7043,
    "volume": 118738500
}, {
    "amount": 1602303582.4,
    "date": 1639113540000,
    "index": 140,
    "price": 3664.0391,
    "volume": 116718500
}, {
    "amount": 1774034758.4,
    "date": 1639113600000,
    "index": 141,
    "price": 3664.6805,
    "volume": 122832600
}, {
    "amount": 1721596228.4,
    "date": 1639113660000,
    "index": 142,
    "price": 3664.6766,
    "volume": 124484100
}, {
    "amount": 1587994755.4,
    "date": 1639113720000,
    "index": 143,
    "price": 3664.6684,
    "volume": 112845000
}, {
    "amount": 1668537781.4,
    "date": 1639113780000,
    "index": 144,
    "price": 3665.2384,
    "volume": 115630900
}, {
    "amount": 1806794939.9,
    "date": 1639113840000,
    "index": 145,
    "price": 3663.2456,
    "volume": 134545400
}, {
    "amount": 1812127042.3,
    "date": 1639113900000,
    "index": 146,
    "price": 3664.1871,
    "volume": 130787700
}, {
    "amount": 1683423722.2,
    "date": 1639113960000,
    "index": 147,
    "price": 3664.3534,
    "volume": 126743100
}, {
    "amount": 1676130454,
    "date": 1639114020000,
    "index": 148,
    "price": 3665.5913,
    "volume": 113372300
}, {
    "amount": 1680920885.9,
    "date": 1639114080000,
    "index": 149,
    "price": 3665.8191,
    "volume": 119193200
}, {
    "amount": 1452179454.5,
    "date": 1639114140000,
    "index": 150,
    "price": 3665.4846,
    "volume": 102503600
}, {
    "amount": 1828846537,
    "date": 1639114200000,
    "index": 151,
    "price": 3665.1433,
    "volume": 143605900
}, {
    "amount": 1610873377.1,
    "date": 1639114260000,
    "index": 152,
    "price": 3664.5323,
    "volume": 121160400
}, {
    "amount": 1558592127.5,
    "date": 1639114320000,
    "index": 153,
    "price": 3664.6928,
    "volume": 114875000
}, {
    "amount": 1520681086.2,
    "date": 1639114380000,
    "index": 154,
    "price": 3664.5842,
    "volume": 111702000
}, {
    "amount": 1697070011.5,
    "date": 1639114440000,
    "index": 155,
    "price": 3664.6973,
    "volume": 121366600
}, {
    "amount": 1796227065.1,
    "date": 1639114500000,
    "index": 156,
    "price": 3665.535,
    "volume": 126917700
}, {
    "amount": 1666914665.9,
    "date": 1639114560000,
    "index": 157,
    "price": 3664.6769,
    "volume": 116590600
}, {
    "amount": 1878460799.3,
    "date": 1639114620000,
    "index": 158,
    "price": 3663.7303,
    "volume": 141816400
}, {
    "amount": 1641417899.3,
    "date": 1639114680000,
    "index": 159,
    "price": 3663.9388,
    "volume": 115665200
}, {
    "amount": 1681817213.1,
    "date": 1639114740000,
    "index": 160,
    "price": 3664.5045,
    "volume": 126262900
}, {
    "amount": 1939135667,
    "date": 1639114800000,
    "index": 161,
    "price": 3665.3084,
    "volume": 138442000
}, {
    "amount": 1665861953.8,
    "date": 1639114860000,
    "index": 162,
    "price": 3664.9372,
    "volume": 113061200
}, {
    "amount": 1582129480.3,
    "date": 1639114920000,
    "index": 163,
    "price": 3664.7514,
    "volume": 113436200
}, {
    "amount": 1767291180.1,
    "date": 1639114980000,
    "index": 164,
    "price": 3663.3524,
    "volume": 126888100
}, {
    "amount": 1605883338.1,
    "date": 1639115040000,
    "index": 165,
    "price": 3662.8563,
    "volume": 125612200
}, {
    "amount": 1744962255.8,
    "date": 1639115100000,
    "index": 166,
    "price": 3663.5799,
    "volume": 117638600
}, {
    "amount": 1626463865.3,
    "date": 1639115160000,
    "index": 167,
    "price": 3664.03,
    "volume": 123601900
}, {
    "amount": 1534411795.9,
    "date": 1639115220000,
    "index": 168,
    "price": 3664.1117,
    "volume": 118662500
}, {
    "amount": 1606600250.2,
    "date": 1639115280000,
    "index": 169,
    "price": 3663.1462,
    "volume": 110997900
}, {
    "amount": 1688702475,
    "date": 1639115340000,
    "index": 170,
    "price": 3664.3729,
    "volume": 118670300
}, {
    "amount": 1768057571.6,
    "date": 1639115400000,
    "index": 171,
    "price": 3664.5971,
    "volume": 137256000
}, {
    "amount": 1672507155.5,
    "date": 1639115460000,
    "index": 172,
    "price": 3663.5035,
    "volume": 125652000
}, {
    "amount": 1621639256.6,
    "date": 1639115520000,
    "index": 173,
    "price": 3662.7596,
    "volume": 118243700
}, {
    "amount": 1739646993.9,
    "date": 1639115580000,
    "index": 174,
    "price": 3662.6968,
    "volume": 122799300
}, {
    "amount": 1656076449.4,
    "date": 1639115640000,
    "index": 175,
    "price": 3662.5276,
    "volume": 124576700
}, {
    "amount": 1663995766.9,
    "date": 1639115700000,
    "index": 176,
    "price": 3663.7077,
    "volume": 121007200
}, {
    "amount": 1556030212.1,
    "date": 1639115760000,
    "index": 177,
    "price": 3662.5389,
    "volume": 111526900
}, {
    "amount": 1647397347.8,
    "date": 1639115820000,
    "index": 178,
    "price": 3662.9031,
    "volume": 111712900
}, {
    "amount": 1468618795.7,
    "date": 1639115880000,
    "index": 179,
    "price": 3662.2401,
    "volume": 104082400
}, {
    "amount": 1612592633.8,
    "date": 1639115940000,
    "index": 180,
    "price": 3662.2865,
    "volume": 107363100
}, {
    "amount": 1710850939.9,
    "date": 1639116000000,
    "index": 181,
    "price": 3661.614,
    "volume": 110406700
}, {
    "amount": 2051674058.1,
    "date": 1639116060000,
    "index": 182,
    "price": 3659.2849,
    "volume": 155272800
}, {
    "amount": 1995391569.5,
    "date": 1639116120000,
    "index": 183,
    "price": 3658.6811,
    "volume": 149065500
}, {
    "amount": 1811852811.3,
    "date": 1639116180000,
    "index": 184,
    "price": 3658.7781,
    "volume": 126435500
}]
